dots/__init__.py
dots/__main__.py
dots/checker.py
dots/cli.py
dots/config.py
dots/logging.py
dots/repository.py
dots/utils.py
dots-0.0.1a0.dist-info/LICENSE
dots-0.0.1a0.dist-info/WHEEL
dots-0.0.1a0.dist-info/METADATA
dots-0.0.1a0.dist-info/RECORD
